{
    "boxShadow": "{{appsmith.theme.boxShadow.appBoxShadow}}",
    "mobileBottomRow": 56,
    "widgetName": "Container1",
    "borderColor": "#E0DEDE",
    "isCanvas": true,
    "displayName": "Container",
    "iconSVG": "https://appcdn.appsmith.com/static/media/icon.c47c069fe28eb6d2d27f0fffdc053074.svg",
    "searchTags": [
        "div",
        "parent",
        "group"
    ],
    "topRow": 15,
    "bottomRow": 71,
    "parentRowSpace": 10,
    "type": "CONTAINER_WIDGET",
    "hideCard": false,
    "shouldScrollContents": true,
    "mobileRightColumn": 18,
    "animateLoading": true,
    "parentColumnSpace": 12.578125,
    "dynamicTriggerPathList": [],
    "leftColumn": 0,
    "dynamicBindingPathList": [
        {"key": "borderRadius"},
        {"key": "boxShadow"}
    ],
    "children": [{
        "mobileBottomRow": 100,
        "widgetName": "Canvas1",
        "displayName": "Canvas",
        "topRow": 0,
        "bottomRow": 560,
        "parentRowSpace": 1,
        "type": "CANVAS_WIDGET",
        "canExtend": false,
        "hideCard": true,
        "minHeight": 100,
        "mobileRightColumn": 226.40625,
        "parentColumnSpace": 1,
        "leftColumn": 0,
        "dynamicBindingPathList": [],
        "key": "sa376p9rov",
        "isDeprecated": false,
        "rightColumn": 226.40625,
        "detachFromLayout": true,
        "widgetId": "nd1hn11cgk",
        "containerStyle": "none",
        "minWidth": 450,
        "isVisible": true,
        "version": 1,
        "parentId": "4y9td8ovnx",
        "renderMode": "CANVAS",
        "isLoading": false,
        "mobileTopRow": 0,
        "responsiveBehavior": "fill",
        "mobileLeftColumn": 0,
        "flexLayers": []
    }],
    "borderWidth": "1",
    "flexVerticalAlignment": "start",
    "key": "7zcn4mss1j",
    "backgroundColor": "#FFFFFF",
    "isDeprecated": false,
    "rightColumn": 31,
    "dynamicHeight": "AUTO_HEIGHT",
    "widgetId": "4y9td8ovnx",
    "containerStyle": "card",
    "minWidth": 450,
    "isVisible": true,
    "version": 1,
    "parentId": "0",
    "renderMode": "CANVAS",
    "isLoading": false,
    "mobileTopRow": 46,
    "responsiveBehavior": "fill",
    "originalTopRow": 15,
    "borderRadius": "{{appsmith.theme.borderRadius.appBorderRadius}}",
    "mobileLeftColumn": 0,
    "maxDynamicHeight": 9000,
    "originalBottomRow": 71,
    "minDynamicHeight": 10
}